namedivider/__init__.py
namedivider/cli.py
namedivider/util.py
namedivider/version.py
namedivider/beta_bert_divider/README.md
namedivider/beta_bert_divider/__init__.py
namedivider/beta_bert_divider/bert_name_divider_only_katakana.py
namedivider/beta_bert_divider/combined_name_divider.py
namedivider/divider/__init__.py
namedivider/divider/basic_name_divider.py
namedivider/divider/config.py
namedivider/divider/divided_name.py
namedivider/divider/gbdt_name_divider.py
namedivider/divider/name_divider_base.py
namedivider/divider/rust_backend.py
namedivider/feature/__init__.py
namedivider/feature/extractor.py
namedivider/feature/family_name.py
namedivider/feature/functional.py
namedivider/feature/kanji.py
namedivider/rule/__init__.py
namedivider/rule/kanji_kana_rule.py
namedivider/rule/pipeline.py
namedivider/rule/rule.py
namedivider/rule/specific_family_name_rule.py
namedivider/rule/specific_given_name_rule.py
namedivider/rule/two_char_rule.py
namedivider/training/__init__.py
namedivider/training/kanji_statistics_taker.py
namedivider/assets/kanji.csv
namedivider/beta_bert_divider/config.json
namedivider/beta_bert_divider/vocab.json
namedivider_python-0.4.1.dist-info/METADATA
namedivider_python-0.4.1.dist-info/WHEEL
namedivider_python-0.4.1.dist-info/entry_points.txt
namedivider_python-0.4.1.dist-info/licenses/LICENSE
namedivider_python-0.4.1.dist-info/RECORD
