Metadata-Version: 2.4
Name: namedivider-python
Version: 0.4.1
Summary: A tool that divides Japanese full names into family and given names.
Project-URL: Homepage, https://github.com/rskmoi/namedivider-python
Author-email: rskmoi <rei.sakamoto.92@gmail.com>
License-Expression: MIT
License-File: LICENSE
Classifier: License :: OSI Approved :: MIT License
Classifier: Programming Language :: Python :: 3.9
Classifier: Programming Language :: Python :: 3.10
Classifier: Programming Language :: Python :: 3.11
Classifier: Programming Language :: Python :: 3.12
Classifier: Programming Language :: Python :: 3.13
Classifier: Programming Language :: Python :: 3.14
Requires-Dist: lightgbm>=3.3
Requires-Dist: numpy
Requires-Dist: pandas
Requires-Dist: regex
Requires-Dist: typer>=0.3.2
